coreason_sentinel/__init__.py
coreason_sentinel/circuit_breaker.py
coreason_sentinel/drift_engine.py
coreason_sentinel/ingestor.py
coreason_sentinel/interfaces.py
coreason_sentinel/main.py
coreason_sentinel/mocks.py
coreason_sentinel/models.py
coreason_sentinel/spot_checker.py
coreason_sentinel/utils/__init__.py
coreason_sentinel/utils/context.py
coreason_sentinel/utils/logger.py
coreason_sentinel-0.3.0.dist-info/METADATA
coreason_sentinel-0.3.0.dist-info/WHEEL
coreason_sentinel-0.3.0.dist-info/licenses/LICENSE
coreason_sentinel-0.3.0.dist-info/licenses/NOTICE
coreason_sentinel-0.3.0.dist-info/RECORD
