Metadata-Version: 2.4
Name: coreason_sentinel
Version: 0.3.0
Summary: alerts you when things go wrong in production
License: # The Prosperity Public License 3.0.0
License-File: LICENSE
License-File: NOTICE
Author: Gowtham A Rao
Author-email: gowtham.rao@coreason.ai
Requires-Python: >=3.11
Classifier: License :: Other/Proprietary License
Classifier: Programming Language :: Python :: 3.12
Classifier: Operating System :: OS Independent
Requires-Dist: aiofiles
Requires-Dist: anyio (>=4.12.1,<5.0.0)
Requires-Dist: coreason-identity
Requires-Dist: fastapi (>=0.128.0,<0.129.0)
Requires-Dist: httpx (>=0.28.1,<0.29.0)
Requires-Dist: loguru (>=0.7.3,<0.8.0)
Requires-Dist: numpy (>=2.4.1,<3.0.0)
Requires-Dist: pydantic (>=2.12.5,<3.0.0)
Requires-Dist: redis (>=7.1.0,<8.0.0)
Requires-Dist: scipy (>=1.17.0,<2.0.0)
Requires-Dist: uvicorn (>=0.40.0,<0.41.0)
Project-URL: Documentation, https://github.com/CoReason-AI/coreason_sentinel
Project-URL: Homepage, https://github.com/CoReason-AI/coreason_sentinel
Project-URL: Repository, https://github.com/CoReason-AI/coreason_sentinel
